mdns/__init__.py
mdns/cli.py
mdns/main.py
mdns/services/__init__.py
mdns/services/networks.py
mdns/utils/__init__.py
mdns/utils/dns.py
macos_dns_switcher-1.0.0.dist-info/METADATA
macos_dns_switcher-1.0.0.dist-info/WHEEL
macos_dns_switcher-1.0.0.dist-info/entry_points.txt
macos_dns_switcher-1.0.0.dist-info/top_level.txt
macos_dns_switcher-1.0.0.dist-info/RECORD
