Metadata-Version: 2.4
Name: macos-dns-switcher
Version: 1.0.0
Summary: CLI tool to switch DNS providers for macOS network services
Author: JimmyMtl
License: MIT
Requires-Python: >=3.7
Requires-Dist: click>=8.1.8
